pycleancode/__init__.py
pycleancode/brace_linter/__init__.py
pycleancode/brace_linter/analyzer.py
pycleancode/brace_linter/cli.py
pycleancode/brace_linter/exceptions/__init__.py
pycleancode/brace_linter/exceptions/errors.py
pycleancode/brace_linter/filesystem/__init__.py
pycleancode/brace_linter/filesystem/file_loader.py
pycleancode/brace_linter/parser/__init__.py
pycleancode/brace_linter/parser/parser_engine.py
pycleancode/brace_linter/reporter/__init__.py
pycleancode/brace_linter/reporter/formatter.py
pycleancode/brace_linter/reports/__init__.py
pycleancode/brace_linter/reports/console_reporter.py
pycleancode/brace_linter/reports/depth_chart_reporter.py
pycleancode/brace_linter/reports/models.py
pycleancode/brace_linter/reports/structure_reporter.py
pycleancode/brace_linter/reports/summary_report.py
pycleancode/brace_linter/rules/__init__.py
pycleancode/brace_linter/rules/loader.py
pycleancode/brace_linter/rules/max_depth_rule.py
pycleancode/brace_linter/rules/nested_function_rule.py
pycleancode/brace_linter/rules/registry.py
pycleancode/brace_linter/rules/rule_base.py
pycleancode/brace_linter/rules/rule_engine.py
pycleancode/brace_linter/rules/violation_model.py
pycleancode/brace_linter/vbtree/__init__.py
pycleancode/brace_linter/vbtree/vbt_builder.py
pycleancode/brace_linter/vbtree/vbt_model.py
pycleancode/core/__init__.py
pycleancode/core/config.py
pycleancode/utils/__init__.py
pycleancode-1.0.2.dist-info/LICENSE
pycleancode-1.0.2.dist-info/METADATA
pycleancode-1.0.2.dist-info/WHEEL
pycleancode-1.0.2.dist-info/entry_points.txt
pycleancode-1.0.2.dist-info/RECORD
