Metadata-Version: 2.3
Name: pycleancode
Version: 1.0.2
Summary: Pycleancode Python toolkit to help developers write professional-grade, maintainable, and clean code following clean code principles
License: MIT
Keywords: linter,clean-code,python,code-quality,static-analysis,oss
Author: Pycleancode
Author-email: admin@pycleancode.com
Requires-Python: >=3.9,<3.13
Classifier: License :: OSI Approved :: MIT License
Classifier: Programming Language :: Python :: 3
Classifier: Programming Language :: Python :: 3.9
Classifier: Programming Language :: Python :: 3.10
Classifier: Programming Language :: Python :: 3.11
Classifier: Programming Language :: Python :: 3.12
Requires-Dist: annotated-types (>=0.4.0)
Requires-Dist: click (==8.1.3)
Requires-Dist: libcst (==1.2.0)
Requires-Dist: markdown-it-py (>=2.2.0)
Requires-Dist: mdurl (>=0.1,<0.2)
Requires-Dist: mypy-extensions (>=0.3.0)
Requires-Dist: pydantic (==2.7.1)
Requires-Dist: pygments (>=2.13.0,<3.0.0)
Requires-Dist: pyyaml (==6.0.1)
Requires-Dist: rich (==13.7.1)
Requires-Dist: typer (==0.7.0)
Requires-Dist: types-pyyaml (>=6.0.12.20250516,<7.0.0.0)
Requires-Dist: typing-extensions (>=3.7.4.2)
Requires-Dist: typing-inspect (==0.9.0)
Project-URL: Repository, https://github.com/pycleancode/pycleancode
